xiaohao_mcpadd_demo/__init__.py
xiaohao_mcpadd_demo-0.1.0.dist-info/WHEEL
xiaohao_mcpadd_demo-0.1.0.dist-info/entry_points.txt
xiaohao_mcpadd_demo-0.1.0.dist-info/METADATA
xiaohao_mcpadd_demo-0.1.0.dist-info/RECORD
